README.md
setup.cfg
setup.py
channelengine_merchant_api_client/__init__.py
channelengine_merchant_api_client/api_client.py
channelengine_merchant_api_client/configuration.py
channelengine_merchant_api_client/exceptions.py
channelengine_merchant_api_client/model_utils.py
channelengine_merchant_api_client/rest.py
channelengine_merchant_api_client.egg-info/PKG-INFO
channelengine_merchant_api_client.egg-info/SOURCES.txt
channelengine_merchant_api_client.egg-info/dependency_links.txt
channelengine_merchant_api_client.egg-info/requires.txt
channelengine_merchant_api_client.egg-info/top_level.txt
channelengine_merchant_api_client/api/__init__.py
channelengine_merchant_api_client/api/cancellation_api.py
channelengine_merchant_api_client/api/channels_api.py
channelengine_merchant_api_client/api/competition_price_api.py
channelengine_merchant_api_client/api/listed_products_api.py
channelengine_merchant_api_client/api/notification_api.py
channelengine_merchant_api_client/api/offer_api.py
channelengine_merchant_api_client/api/order_api.py
channelengine_merchant_api_client/api/product_api.py
channelengine_merchant_api_client/api/product_bundle_api.py
channelengine_merchant_api_client/api/return_api.py
channelengine_merchant_api_client/api/settings_api.py
channelengine_merchant_api_client/api/shipment_api.py
channelengine_merchant_api_client/api/stock_location_api.py
channelengine_merchant_api_client/api/webhook_api.py
channelengine_merchant_api_client/apis/__init__.py
channelengine_merchant_api_client/model/__init__.py
channelengine_merchant_api_client/model/advance_settings_response.py
channelengine_merchant_api_client/model/api_response.py
channelengine_merchant_api_client/model/channel_carrier_collection_method_api.py
channelengine_merchant_api_client/model/channel_carrier_recommendation_api.py
channelengine_merchant_api_client/model/channel_channel_response.py
channelengine_merchant_api_client/model/channel_global_channel_response.py
channelengine_merchant_api_client/model/channel_listed_product_response.py
channelengine_merchant_api_client/model/collection_of_channel_global_channel_response.py
channelengine_merchant_api_client/model/collection_of_channel_listed_product_response.py
