Metadata-Version: 1.2
Name: channelengine-merchant-api-client
Version: 2.13.0
Summary: ChannelEngine Merchant API
Home-page: https://github.com/channelengine/merchant-api-client-python
Author: OpenAPI Generator community
Author-email: team@openapitools.org
License: UNKNOWN
Keywords: OpenAPI,OpenAPI-Generator,ChannelEngine Merchant API
Platform: UNKNOWN
Requires-Python: >=3.6
